<?xml version='1.0' encoding='UTF-8'?>
<document>
	<title><![CDATA[Sélection Equipe départementale]]></title>
	<allow_com>1</allow_com>
	<template><![CDATA[article.php]]></template>
	<chapo><![CDATA[<p>Les sélections pour intégrer l'<strong>équipe départementale FFME</strong> avait lieu samedi 20 octobre 2012.</p>]]></chapo>
	<content><![CDATA[<p>Il s'agissait de faire partie des 12 meilleurs grimpeurs de l'Isère répartis sur les catégories benjamins/benjamines, minimes et cadet/cadettes. Les jeunes ont du faire leurs preuves sur 4 voies allant de 6b à 7c à Espace vertical 3.</p>

<p>Bravo à Matéo et Maëlle qui gagnent ces sélections ! Félicitations aussi à Paul, Méris, Marine, Bastien et Anouk qui sont eux aussi sélectionnés en équipe départementale.</p>

<p>Manon, Quentin et Tom intègrent l'équipe en tant que remplaçants : ils seront convoqués aux entraînements en cas de désistement d'un des membres de l'équipe.&nbsp;</p>]]></content>
	<tags><![CDATA[]]></tags>
	<meta_description><![CDATA[]]></meta_description>
	<meta_keywords><![CDATA[]]></meta_keywords>
	<title_htmltag><![CDATA[]]></title_htmltag>
	<thumbnail><![CDATA[data/medias/news/default.png]]></thumbnail>
	<thumbnail_alt><![CDATA[]]></thumbnail_alt>
	<thumbnail_title><![CDATA[]]></thumbnail_title>
	<date_creation><![CDATA[201607301718]]></date_creation>
	<date_update><![CDATA[201607301835]]></date_update>
</document>