<?xml version='1.0' encoding='UTF-8'?>
<document>
	<title><![CDATA[Championnat régional de bloc 2015]]></title>
	<allow_com>1</allow_com>
	<template><![CDATA[article.php]]></template>
	<chapo><![CDATA[<p>Le fait marquant du WE : &nbsp;Tanguy gagne dans la catégorie la plus relevé : Sénior !&nbsp;</p>]]></chapo>
	<content><![CDATA[<p>Du côté des plus jeunes : Matéo et Méris empochent leur&nbsp;ticket pour le Chpt.&nbsp;de France en se classant respectivement 8ième et 5ième. Tristant L,&nbsp;<span style="font-size:14px;"><strong><u>récemment médaillé de bronze au dernier Chpt. du monde Junior</u></strong></span> d'escalade sur&nbsp;cascade de glace, loupe sa qualification au France pour un essai de trop sur une zone... et se classe 11ième. Quelques regrets surement, mais le niveau est là !</p>

<p>Belle perf également de Maëlle (13ième) et Quentin (16ième). Le meilleur classement du côté des minimes filles est pour Sophie : 24ième.&nbsp;<span style="line-height: 1.6em;">Du côte des vieux, Fabien prend la 6ième place.</span><br />
&nbsp;</p>

<p><a class="button icon fa-trophy" href="http://www.ffme.fr/uploads/escalade/resultats/2015/bloc/2015-chpt-reg-bloc-rhone-alpes.pdf">Résultats</a></p>]]></content>
	<tags><![CDATA[]]></tags>
	<meta_description><![CDATA[]]></meta_description>
	<meta_keywords><![CDATA[]]></meta_keywords>
	<title_htmltag><![CDATA[]]></title_htmltag>
	<thumbnail><![CDATA[data/medias/news/default.png]]></thumbnail>
	<thumbnail_alt><![CDATA[]]></thumbnail_alt>
	<thumbnail_title><![CDATA[]]></thumbnail_title>
	<date_creation><![CDATA[201607301801]]></date_creation>
	<date_update><![CDATA[201607301810]]></date_update>
</document>